sftpd/__init__.py
sftpd/application.py
sftpd/server.py
sftpd/simple.py
sftpd/utils.py
sftpd-0.2.0.dist-info/LICENSE
sftpd-0.2.0.dist-info/METADATA
sftpd-0.2.0.dist-info/WHEEL
sftpd-0.2.0.dist-info/entry_points.txt
sftpd-0.2.0.dist-info/top_level.txt
sftpd-0.2.0.dist-info/RECORD
