Metadata-Version: 2.1
Name: sftpd
Version: 0.2.0
Summary: A simple multi-thread sftp server.
Home-page: UNKNOWN
Author: zencore
Author-email: dobetter@zencore.cn
License: MIT
Keywords: sftpd
Platform: UNKNOWN
Classifier: Development Status :: 5 - Production/Stable
Classifier: Intended Audience :: Developers
Classifier: Topic :: Software Development :: Libraries :: Python Modules
Classifier: License :: OSI Approved :: MIT License
Classifier: Programming Language :: Python :: 3
Classifier: Programming Language :: Python :: 3 :: Only
License-File: LICENSE
Requires-Dist: click
Requires-Dist: paramiko
Requires-Dist: pyyaml
Requires-Dist: dictop
Requires-Dist: appserver
